quantum_viz/__init__.py
quantum_viz/py.typed
quantum_viz/qiskit_parser.py
quantum_viz/utils.py
quantum_viz/widget.py
quantum_viz-1.0.5.dist-info/LICENSE.txt
quantum_viz-1.0.5.dist-info/WHEEL
quantum_viz-1.0.5.dist-info/METADATA
quantum_viz-1.0.5.dist-info/RECORD
