Metadata-Version: 2.1
Name: quantum-viz
Version: 1.0.5
Summary: quantum-viz.js Python tools
Home-page: https://github.com/microsoft/quantum-viz.js
License: MIT
Author: Microsoft Corporation
Author-email: que-contacts@microsoft.com
Requires-Python: >=3.8,<4.0
Classifier: Development Status :: 3 - Alpha
Classifier: License :: OSI Approved :: MIT License
Classifier: Programming Language :: Python :: 3
Classifier: Programming Language :: Python :: 3.10
Classifier: Programming Language :: Python :: 3.8
Classifier: Programming Language :: Python :: 3.9
Provides-Extra: qiskit
Requires-Dist: click (>=8.0.1,<9.0.0)
Requires-Dist: ipython (>=8.0.3,<9.0.0)
Requires-Dist: qiskit-terra (>=0.19.1,<1); extra == "qiskit"
Requires-Dist: varname (>=0.8.1,<0.9.0)
Project-URL: Changelog, https://github.com/microsoft/quantum-viz.js/releases
Project-URL: Documentation, https://github.com/microsoft/quantum-viz.js
Project-URL: Repository, https://github.com/microsoft/quantum-viz.js
